asmai/__init__.py
asmai/anasem.py
asmai/sem_const.py
asmai/semdictionary.py
asmai/data/semantic.sqlite
asmai-0.1.dist-info/METADATA
asmai-0.1.dist-info/RECORD
asmai-0.1.dist-info/WHEEL
asmai-0.1.dist-info/top_level.txt
