Metadata-Version: 2.1
Name: asmai
Version: 0.1
Summary: Asmai: (Al'asma'i) Arabic semantic analysis library for Python
Home-page: http://asmai.sourceforge.net/
Author: Taha Zerrouki
Author-email: taha.zerrouki@gmail.com
License: GPL
Platform: UNKNOWN
Classifier: Development Status :: 5 - Production/Stable
Classifier: Intended Audience :: End Users/Desktop
Classifier: Operating System :: OS Independent
Classifier: Programming Language :: Python
Requires-Dist: pyarabic (>=0.6.2)
